{
    "product": "Lời kinh trong bữa ăn gia đình",
    "version": 1,
    "releaseDate": "2024-01-01T00:00:00.000Z",
    "demo": true,
    "section": [
      {
        "id": 1,
        "title": "Trang bìa",
        "page": [1],
        "url": ["Loi kinh bua an gia dinh_page-0001.jpg"]
      },
      {
        "id": 1,
        "title": "Lời giới thiệu",
        "page": [3],
        "url": ["Loi kinh bua an gia dinh_page-0003.jpg"]
      },
      {
        "id": 2,
        "title": "Lời mở đầu",
        "page": [5,6],
        "url": ["Loi kinh bua an gia dinh_page-0005.jpg", "Loi kinh bua an gia dinh_page-0006.jpg"]
      },
      {
        "id": 3,
        "title": "Phần I: Các lời kinh bữa ăn hàng ngày",
        "page": [7],
        "url": ["Loi kinh bua an gia dinh_page-0007.jpg"],
        "chap": [
          {
            "id_number": 1,
            "title": "Lời kinh số 1",
            "page": [8],
            "url": ["Loi kinh bua an gia dinh_page-0008.jpg"]
          },
          {
            "id_number": 2,
            "title": "Lời kinh số 2",
            "page": [9],
            "url": ["Loi kinh bua an gia dinh_page-0009.jpg"]
          },
          {
            "id_number": 3,
            "title": "Lời kinh số 3",
            "page": [10],
            "url": ["Loi kinh bua an gia dinh_page-0010.jpg"]
          },
          {
            "id_number": 4,
            "title": "Lời kinh số 4",
            "page": [11],
            "url": ["Loi kinh bua an gia dinh_page-0011.jpg"]
          },
          {
            "id_number": 5,
            "title": "Lời kinh số 5",
            "page": [12],
            "url": ["Loi kinh bua an gia dinh_page-0012.jpg"]
          },
          {
            "id_number": 6,
            "title": "Lời kinh số 6",
            "page": [13],
            "url": ["Loi kinh bua an gia dinh_page-0013.jpg"]
          },
          {
            "id_number": 7,
            "title": "Lời kinh số 7",
            "page": [14],
            "url": ["Loi kinh bua an gia dinh_page-0014.jpg"]
          },
          {
            "id_number": 8,
            "title": "Lời kinh số 8",
            "page": [15],
            "url": ["Loi kinh bua an gia dinh_page-0015.jpg"]
          },
          {
            "id_number": 9,
            "title": "Lời kinh số 9",
            "page": [16],
            "url": ["Loi kinh bua an gia dinh_page-0016.jpg"]
          },
          {
            "id_number": 10,
            "title": "Lời kinh số 10",
            "page": [17],
            "url": ["Loi kinh bua an gia dinh_page-0017.jpg"]
          },
          {
            "id_number": 11,
            "title": "Lời kinh số 11",
            "page": [18],
            "url": ["Loi kinh bua an gia dinh_page-0018.jpg"]
          },
          {
            "id_number": 12,
            "title": "Lời kinh số 12",
            "page": [19],
            "url": ["Loi kinh bua an gia dinh_page-0019.jpg"]
          },
          {
            "id_number": 13,
            "title": "Lời kinh số 13",
            "page": [20],
            "url": ["Loi kinh bua an gia dinh_page-0020.jpg"]
          },
          {
            "id_number": 14,
            "title": "Lời kinh số 14",
            "page": [21],
            "url": ["Loi kinh bua an gia dinh_page-0021.jpg"]
          },
          {
            "id_number": 15,
            "title": "Lời kinh số 15",
            "page": [22],
            "url": ["Loi kinh bua an gia dinh_page-0022.jpg"]
          },
          {
            "id_number": 16,
            "title": "Lời kinh số 16",
            "page": [23],
            "url": ["Loi kinh bua an gia dinh_page-0023.jpg"]
          },
          {
            "id_number": 17,
            "title": "Lời kinh số 17",
            "page": [24],
            "url": ["Loi kinh bua an gia dinh_page-0024.jpg"]
          },
          {
            "id_number": 18,
            "title": "Lời kinh số 18",
            "page": [25],
            "url": ["Loi kinh bua an gia dinh_page-0025.jpg"]
          },
          {
            "id_number": 19,
            "title": "Lời kinh số 19",
            "page": [26],
            "url": ["Loi kinh bua an gia dinh_page-0026.jpg"]
          },
          {
            "id_number": 20,
            "title": "Lời kinh số 20",
            "page": [27],
            "url": ["Loi kinh bua an gia dinh_page-0027.jpg"]
          },
          {
            "id_number": 21,
            "title": "Lời kinh số 21",
            "page": [28],
            "url": ["Loi kinh bua an gia dinh_page-0028.jpg"]
          },
          {
            "id_number": 22,
            "title": "Lời kinh số 22",
            "page": [29],
            "url": ["Loi kinh bua an gia dinh_page-0029.jpg"]
          },
          {
            "id_number": 23,
            "title": "Lời kinh số 23",
            "page": [30],
            "url": ["Loi kinh bua an gia dinh_page-0030.jpg"]
          },
          {
            "id_number": 24,
            "title": "Lời kinh số 24",
            "page": [31],
            "url": ["Loi kinh bua an gia dinh_page-0031.jpg"]
          },
          {
            "id_number": 25,
            "title": "Lời kinh số 25",
            "page": [32],
            "url": ["Loi kinh bua an gia dinh_page-0032.jpg"]
          },
          {
            "id_number": 26,
            "title": "Lời kinh số 26",
            "page": [33],
            "url": ["Loi kinh bua an gia dinh_page-0033.jpg"]
          },
          {
            "id_number": 27,
            "title": "Lời kinh số 27",
            "page": [34],
            "url": ["Loi kinh bua an gia dinh_page-0034.jpg"]
          },
          {
            "id_number": 28,
            "title": "Lời kinh số 28",
            "page": [35],
            "url": ["Loi kinh bua an gia dinh_page-0035.jpg"]
          },
          {
            "id_number": 29,
            "title": "Lời kinh số 29",
            "page": [36],
            "url": ["Loi kinh bua an gia dinh_page-0036.jpg"]
          },
          {
            "id_number": 30,
            "title": "Lời kinh số 30",
            "page": [37],
            "url": ["Loi kinh bua an gia dinh_page-0037.jpg"]
          },
          {
            "id_number": 31,
            "title": "Lời kinh số 31",
            "page": [38],
            "url": ["Loi kinh bua an gia dinh_page-0038.jpg"]
          },
          {
            "id_number": 32,
            "title": "Lời kinh số 32",
            "page": [39],
            "url": ["Loi kinh bua an gia dinh_page-0039.jpg"]
          },
          {
            "id_number": 33,
            "title": "Lời kinh số 33",
            "page": [40],
            "url": ["Loi kinh bua an gia dinh_page-0040.jpg"]
          },
          {
            "id_number": 34,
            "title": "Lời kinh số 34",
            "page": [41],
            "url": ["Loi kinh bua an gia dinh_page-0041.jpg"]
          },
          {
            "id_number": 35,
            "title": "Lời kinh số 35",
            "page": [42],
            "url": ["Loi kinh bua an gia dinh_page-0042.jpg"]
          },
          {
            "id_number": 36,
            "title": "Lời kinh số 36",
            "page": [43],
            "url": ["Loi kinh bua an gia dinh_page-0043.jpg"]
          },
          {
            "id_number": 37,
            "title": "Lời kinh số 37",
            "page": [44],
            "url": ["Loi kinh bua an gia dinh_page-0044.jpg"]
          },
          {
            "id_number": 38,
            "title": "Lời kinh số 38",
            "page": [45],
            "url": ["Loi kinh bua an gia dinh_page-0045.jpg"]
          },
          {
            "id_number": 39,
            "title": "Lời kinh số 39",
            "page": [46],
            "url": ["Loi kinh bua an gia dinh_page-0046.jpg"]
          },
          {
            "id_number": 40,
            "title": "Lời kinh số 40",
            "page": [47],
            "url": ["Loi kinh bua an gia dinh_page-0047.jpg"]
          },
          {
            "id_number": 41,
            "title": "Lời kinh số 41",
            "page": [48],
            "url": ["Loi kinh bua an gia dinh_page-0048.jpg"]
          },
          {
            "id_number": 42,
            "title": "Lời kinh số 42",
            "page": [49],
            "url": ["Loi kinh bua an gia dinh_page-0049.jpg"]
          },
          {
            "id_number": 43,
            "title": "Lời kinh số 43",
            "page": [50],
            "url": ["Loi kinh bua an gia dinh_page-0050.jpg"]
          },
          {
            "id_number": 44,
            "title": "Lời kinh số 44",
            "page": [51],
            "url": ["Loi kinh bua an gia dinh_page-0051.jpg"]
          },
          {
            "id_number": 45,
            "title": "Lời kinh số 45",
            "page": [52],
            "url": ["Loi kinh bua an gia dinh_page-0052.jpg"]
          },
          {
            "id_number": 46,
            "title": "Lời kinh số 46",
            "page": [53],
            "url": ["Loi kinh bua an gia dinh_page-0053.jpg"]
          },
          {
            "id_number": 47,
            "title": "Lời kinh số 47",
            "page": [54],
            "url": ["Loi kinh bua an gia dinh_page-0054.jpg"]
          },
          {
            "id_number": 48,
            "title": "Lời kinh số 48",
            "page": [55],
            "url": ["Loi kinh bua an gia dinh_page-0055.jpg"]
          },
          {
            "id_number": 49,
            "title": "Lời kinh số 49",
            "page": [56],
            "url": ["Loi kinh bua an gia dinh_page-0056.jpg"]
          },
          {
            "id_number": 50,
            "title": "Lời kinh số 50",
            "page": [57],
            "url": ["Loi kinh bua an gia dinh_page-0057.jpg"]
          },
          {
            "id_number": 51,
            "title": "Lời kinh số 51",
            "page": [58],
            "url": ["Loi kinh bua an gia dinh_page-0058.jpg"]
          },
          {
            "id_number": 52,
            "title": "Lời kinh số 52",
            "page": [59],
            "url": ["Loi kinh bua an gia dinh_page-0059.jpg"]
          }
        ]
      },
      {
        "id": 4,
        "title": "Phần II: Các lời kinh dịp đặc biệt",
        "page": [61],
        "url": ["Loi kinh bua an gia dinh_page-0061.jpg"],
        "chap": [
          {
            "id": 1,
            "title": "Tất niên - Giao thừa",
            "page": [62],
            "url": ["Loi kinh bua an gia dinh_page-0062.jpg"]
          },
          {
            "id": 2,
            "title": "Mồng 1 Tết",
            "page": [63],
            "url": ["Loi kinh bua an gia dinh_page-0063.jpg"]
          },
          {
            "id": 2,
            "title": "Mồng 2 Tết",
            "page": [64],
            "url": ["Loi kinh bua an gia dinh_page-0064.jpg"]
          },
          {
            "id": 2,
            "title": "Mồng 3 Tết",
            "page": [65],
            "url": ["Loi kinh bua an gia dinh_page-0065.jpg"]
          },
          {
            "id": 2,
            "title": "Giáng Sinh",
            "page": [66],
            "url": ["Loi kinh bua an gia dinh_page-0066.jpg"]
          },
          {
            "id": 2,
            "title": "Phục Sinh",
            "page": [67],
            "url": ["Loi kinh bua an gia dinh_page-0067.jpg"]
          },
          {
            "id": 2,
            "title": "Rửa tội",
            "page": [68],
            "url": ["Loi kinh bua an gia dinh_page-0068.jpg"]
          },
          {
            "id": 2,
            "title": "Rước lễ lần đầu",
            "page": [69],
            "url": ["Loi kinh bua an gia dinh_page-0069.jpg"]
          },
          {
            "id": 2,
            "title": "Thêm sức",
            "page": [70],
            "url": ["Loi kinh bua an gia dinh_page-0070.jpg"]
          },
          {
            "id": 2,
            "title": "Chầu lượt",
            "page": [71],
            "url": ["Loi kinh bua an gia dinh_page-0071.jpg"]
          }
        ]
      }
    ]
  }
  